table2csv
