Metadata-Version: 1.0
Name: table2csv
Version: 0.1.3
Summary: Extract data from an HTML table and store results to a csv file.
Home-page: https://github.com/hernamesbarbara/table2csv
Author: Austin Ogilvie
Author-email: a@yhathq.com
License: MIT
Keywords: Extract HTML tables csv data
Platform: UNKNOWN
